bfloat16.cpython-312-x86_64-linux-gnu.so
bfloat16-1.2.0.dist-info/top_level.txt
bfloat16-1.2.0.dist-info/METADATA
bfloat16-1.2.0.dist-info/LICENSE.txt
bfloat16-1.2.0.dist-info/RECORD
bfloat16-1.2.0.dist-info/WHEEL
